qpacket/__init__.py
qpacket/core.py
qpacket/real_case_barrier.py
qpacket-0.1.0.dist-info/METADATA
qpacket-0.1.0.dist-info/WHEEL
qpacket-0.1.0.dist-info/entry_points.txt
qpacket-0.1.0.dist-info/top_level.txt
qpacket-0.1.0.dist-info/RECORD
