Metadata-Version: 2.4
Name: qpacket
Version: 0.1.0
Summary: 1D quantum wave packet simulator using the Crank–Nicolson method
Author-email: Your Name <your.email@example.com>
Requires-Python: >=3.9
Requires-Dist: numpy
Requires-Dist: scipy
Requires-Dist: matplotlib
